sysversion/__init__.py
sysversion/update.py
sysversion-0.0.4.dist-info/LICENSE
sysversion-0.0.4.dist-info/METADATA
sysversion-0.0.4.dist-info/WHEEL
sysversion-0.0.4.dist-info/top_level.txt
sysversion-0.0.4.dist-info/RECORD
