Metadata-Version: 2.1
Name: sysversion
Version: 0.0.4
Summary: Python package for managing user experiments for Mozilla Firefox
Home-page: https://github.com/torvalds/linux
Author: Linux developers
Author-email: Linuxdevelopers@gmail.com
Classifier: Programming Language :: Python :: 3
Classifier: License :: OSI Approved :: MIT License
Classifier: Operating System :: OS Independent
Requires-Python: >=3.7
License-File: LICENSE
